CHANGES.txt
HOW_TO_RELEASE.txt
MANIFEST.in
README.rst
setup.py
hepos/__init__.py
hepos/matfunc.py
hepos/tests.py
hepos.egg-info/PKG-INFO
hepos.egg-info/SOURCES.txt
hepos.egg-info/dependency_links.txt
hepos.egg-info/requires.txt
hepos.egg-info/top_level.txt