Metadata-Version: 1.0
Name: hepos
Version: 0.1.0
Summary: Greek co-ordinate transformations using the HEPOS algorithm
Home-page: UNKNOWN
Author: Antonis Christofides
Author-email: anthony@itia.ntua.gr
License: GPL3
Platform: UNKNOWN
